mydockeruse/__init__.py
mydockeruse/__main__.py
mydockeruse/install.py
mydockeruse/uninstall.py
mydockeruse-0.0.5.dist-info/LICENSE
mydockeruse-0.0.5.dist-info/METADATA
mydockeruse-0.0.5.dist-info/WHEEL
mydockeruse-0.0.5.dist-info/top_level.txt
mydockeruse-0.0.5.dist-info/RECORD
