Metadata-Version: 2.2
Name: mydockeruse
Version: 0.0.5
Summary: mydockeruse tool
Home-page: https://github.com/FarAway6834/mydockeruse
Author: du7ec
Author-email: dutec6834@gmail.com
Keywords: mydockeruse,mydockeruse tool,mytool4docker
Classifier: Programming Language :: Python :: 3.4
Classifier: Programming Language :: Python :: 3.5
Classifier: Programming Language :: Python :: 3.6
Classifier: Programming Language :: Python :: 3.7
Classifier: Programming Language :: Python :: 3.8
Classifier: Programming Language :: Python :: 3.9
Classifier: Programming Language :: Python :: 3.10
Classifier: Programming Language :: Python :: 3.11
Classifier: Programming Language :: Python :: 3.12
Classifier: Programming Language :: Python :: 3.13
Classifier: Programming Language :: Python :: 3.14
Requires-Python: >=3.4
License-File: LICENSE
Requires-Dist: mytool4docker
Dynamic: author
Dynamic: author-email
Dynamic: classifier
Dynamic: home-page
Dynamic: keywords
Dynamic: requires-dist
Dynamic: requires-python
Dynamic: summary
